<?xml version="1.0" encoding="UTF-8"?>
<alpino_ds version="1.6">
  <parser build="Alpino-x86_64-linux-glibc2.5-git308-sicstus" date="2021-03-05T13:45" cats="1" skips="0" />
  <node begin="0" cat="top" end="10" id="0" rel="top">
    <node begin="0" cat="du" end="9" id="1" rel="--">
      <node begin="0" conjtype="neven" end="1" frame="complementizer(root)" his="normal" his_1="decap" his_1_1="normal" id="2" lcat="du" lemma="en" pos="comp" postag="VG(neven)" pt="vg" rel="dlink" root="en" sc="root" sense="en" word="En"/>
      <node begin="1" cat="cp" end="9" id="3" rel="nucl">
        <node begin="1" conjtype="onder" end="2" frame="complementizer(of)" his="normal" his_1="normal" id="4" lcat="cp" lemma="of" pos="comp" postag="VG(onder)" pt="vg" rel="cmp" root="of" sc="of" sense="of" word="of"/>
        <node begin="2" cat="ssub" end="9" id="5" rel="body">
          <node begin="2" case="both" def="def" end="3" frame="pronoun(nwh,thi,both,de,both,def,wkpro)" gen="de" genus="fem" getal="ev" his="normal" his_1="normal" id="6" index="1" lcat="np" lemma="ze" naamval="stan" num="both" pdtype="pron" per="thi" persoon="3" pos="pron" postag="VNW(pers,pron,stan,red,3,ev,fem)" pt="vnw" rel="su" rnum="sg" root="ze" sense="ze" special="wkpro" status="red" vwtype="pers" wh="nwh" word="ze"/>
          <node begin="5" end="6" frame="verb(hebben,past(sg),aux(inf))" his="normal" his_1="normal" id="7" infl="sg" lcat="ssub" lemma="zullen" pos="verb" postag="WW(pv,verl,ev)" pt="ww" pvagr="ev" pvtijd="verl" rel="hd" root="zal" sc="aux(inf)" sense="zal" tense="past" word="zou" wvorm="pv"/>
          <node begin="2" cat="inf" end="9" id="8" rel="vc">
            <node begin="2" end="3" id="9" index="1" rel="su"/>
            <node begin="6" buiging="zonder" end="7" frame="verb(hebben,inf,transitive_ndev)" his="normal" his_1="normal" id="10" infl="inf" lcat="inf" lemma="hebben" pos="verb" positie="vrij" postag="WW(inf,vrij,zonder)" pt="ww" rel="hd" root="heb" sc="transitive_ndev" sense="heb" word="hebben" wvorm="inf"/>
            <node begin="3" cat="conj" end="9" id="11" rel="obj1">
              <node begin="3" cat="np" end="5" id="12" rel="cnj">
                <node begin="3" end="4" frame="determiner(een)" his="normal" his_1="normal" id="13" infl="een" lcat="detp" lemma="een" lwtype="onbep" naamval="stan" npagr="agr" pos="det" postag="LID(onbep,stan,agr)" pt="lid" rel="det" root="een" sense="een" word="een"/>
                <node begin="4" end="5" frame="noun(het,count,sg)" gen="het" genus="onz" getal="ev" graad="dim" his="normal" his_1="normal" id="14" lcat="np" lemma="kind" naamval="stan" ntype="soort" num="sg" pos="noun" postag="N(soort,ev,dim,onz,stan)" pt="n" rel="hd" rnum="sg" root="kind_DIM" sense="kind_DIM" word="kindje"/>
              </node>
              <node begin="7" conjtype="neven" end="8" frame="conj(of)" his="normal" his_1="normal" id="15" lcat="vg" lemma="of" pos="vg" postag="VG(neven)" pt="vg" rel="crd" root="of" sense="of" word="of"/>
              <node begin="8" end="9" frame="noun(het,count,pl)" gen="het" getal="mv" graad="dim" his="normal" his_1="normal" id="16" lcat="np" lemma="kind" ntype="soort" num="pl" pos="noun" postag="N(soort,mv,dim)" pt="n" rel="cnj" rnum="pl" root="kind_DIM" sense="kind_DIM" word="kindertjes"/>
            </node>
          </node>
        </node>
      </node>
    </node>
    <node begin="9" end="10" frame="punct(punt)" his="normal" his_1="normal" id="17" lcat="punct" lemma="." pos="punct" postag="LET()" pt="let" rel="--" root="." sense="." special="punt" word="."/>
  </node>
  <sentence sentid="50-2">En of ze een kindje zou hebben of kindertjes .</sentence>
  <comments>
    <comment>Q#50-2|En of ze een kindje zou hebben of kindertjes .|1|1|-5.679208890359999</comment>
  </comments>
</alpino_ds>
