<?xml version="1.0" encoding="UTF-8"?>
<alpino_ds version="1.6">
  <parser cats="2" skips="0" />
  <node begin="0" cat="top" end="27" id="0" rel="top">
    <node begin="7" end="8" frame="punct(komma)" his="normal" his_1="normal" id="1" lcat="punct" lemma="," pos="punct" postag="LET()" pt="let" rel="--" root="," sense="," special="komma" word=","/>
    <node begin="19" end="20" frame="punct(aanhaal_both)" his="normal" his_1="normal" id="2" lcat="punct" lemma="&quot;" pos="punct" postag="LET()" pt="let" rel="--" root="&quot;" sense="&quot;" special="aanhaal_both" word="&quot;"/>
    <node begin="24" end="25" frame="punct(aanhaal_both)" his="normal" his_1="normal" id="3" lcat="punct" lemma="&quot;" pos="punct" postag="LET()" pt="let" rel="--" root="&quot;" sense="&quot;" special="aanhaal_both" word="&quot;"/>
    <node begin="0" cat="du" end="26" id="4" rel="--">
      <node begin="0" case="nom" def="def" end="1" frame="pronoun(nwh,fir,sg,de,nom,def)" gen="de" getal="ev" his="normal" his_1="decap" his_1_1="normal" id="5" lcat="np" lemma="ik" naamval="nomin" num="sg" pdtype="pron" per="fir" persoon="1" pos="pron" postag="VNW(pers,pron,nomin,vol,1,ev)" pt="vnw" rel="dp" rnum="sg" root="ik" sense="ik" status="vol" vwtype="pers" wh="nwh" word="Ik"/>
      <node begin="1" cat="sv1" end="26" id="6" rel="dp">
        <node begin="1" end="2" frame="verb(hebben,past(sg),np_np_ld_pp)" his="normal" his_1="normal" id="7" infl="sg" lcat="sv1" lemma="werpen" pos="verb" postag="WW(pv,verl,ev)" pt="ww" pvagr="ev" pvtijd="verl" rel="hd" root="werp" sc="np_np_ld_pp" sense="werp" stype="topic_drop" tense="past" word="wierp" wvorm="pv"/>
        <node begin="2" end="3" frame="er_vp_adverb" getal="getal" his="normal" his_1="normal" id="8" lcat="advp" lemma="er" naamval="stan" pdtype="adv-pron" persoon="3" pos="adv" postag="VNW(aanw,adv-pron,stan,red,3,getal)" pt="vnw" rel="mod" root="er" sense="er" special="er" status="red" vwtype="aanw" word="er"/>
        <node begin="3" case="both" def="indef" end="4" frame="pronoun(nwh,thi,sg,both,both,indef,strpro)" gen="both" his="normal" his_1="normal" id="9" lcat="np" lemma="één" num="sg" numtype="hoofd" per="thi" pos="pron" positie="vrij" postag="TW(hoofd,vrij)" pt="tw" rel="su" rnum="sg" root="één" sense="één" special="strpro" wh="nwh" word="een"/>
        <node aform="base" begin="4" buiging="met-e" end="5" frame="nominalized_adjective" getal-n="mv-n" graad="basis" his="normal" his_1="A-n" id="10" lcat="np" lemma="haastig" num="pl" personalized="true" pos="adj" positie="nom" postag="ADJ(nom,basis,met-e,mv-n)" pt="adj" rel="obj2" rnum="pl" root="haastig" sense="haastig" special="a_noun" word="haastigen"/>
        <node begin="5" end="6" frame="noun(de,count,sg)" gen="de" genus="zijd" getal="ev" graad="basis" his="normal" his_1="normal" id="11" lcat="np" lemma="blik" naamval="stan" ntype="soort" num="sg" pos="noun" postag="N(soort,ev,basis,zijd,stan)" pt="n" rel="obj1" rnum="sg" root="blik" sense="blik" word="blik"/>
        <node begin="6" end="7" frame="preposition(over,[],extracted_np)" his="normal" his_1="normal" id="12" lcat="pp" lemma="overheen" pos="prep" postag="VZ(fin)" pt="vz" rel="ld" root="overheen" sc="extracted_np" sense="overheen" vztype="fin" word="overheen"/>
        <node begin="8" cat="whrel" end="26" id="13" rel="mod">
          <node begin="8" end="9" frame="waar_adverb(bij)" his="normal" his_1="normal" id="14" index="1" lcat="pp" lemma="waarbij" pos="pp" postag="BW()" pt="bw" rel="rhd" root="waarbij" sense="waarbij" special="waar" word="waarbij"/>
          <node begin="8" cat="ssub" end="26" id="15" rel="body">
            <node begin="8" end="9" id="16" index="1" rel="mod"/>
            <node begin="9" case="nom" def="def" end="10" frame="pronoun(nwh,fir,sg,de,nom,def)" gen="de" getal="ev" his="normal" his_1="normal" id="17" lcat="np" lemma="ik" naamval="nomin" num="sg" pdtype="pron" per="fir" persoon="1" pos="pron" postag="VNW(pers,pron,nomin,vol,1,ev)" pt="vnw" rel="su" rnum="sg" root="ik" sense="ik" status="vol" vwtype="pers" wh="nwh" word="ik"/>
            <node begin="10" cat="np" end="24" id="18" rel="obj1">
              <node begin="10" comparative="dan" end="11" frame="comp_noun(het,mass,sg,dan)" gen="het" getal="ev" his="normal" his_1="normal" id="19" lcat="np" lemma="niets" naamval="stan" num="sg" pdtype="pron" persoon="3o" pos="noun" postag="VNW(onbep,pron,stan,vol,3o,ev)" pt="vnw" rel="hd" rnum="sg" root="niets" sense="niets" special="comp" status="vol" vwtype="onbep" word="niets"/>
              <node begin="11" cat="cp" end="24" id="20" rel="obcomp">
                <node begin="11" conjtype="onder" end="12" frame="comparative(dan)" his="normal" his_1="normal" id="21" lcat="comparative" lemma="dan" pos="comparative" postag="VG(onder)" pt="vg" rel="cmp" root="dan" sense="dan" word="dan"/>
                <node begin="12" cat="np" end="24" id="22" rel="body">
                  <node begin="12" end="13" frame="noun(both,both,both)" gen="both" genus="zijd" getal="ev" graad="basis" his="noun" id="23" lcat="np" lemma="betuigingen" naamval="stan" ntype="soort" num="both" pos="noun" postag="N(soort,ev,basis,zijd,stan)" pt="n" rel="hd" rnum="sg" root="betuigingen" sense="betuigingen" word="betuigingen"/>
                  <node begin="13" cat="pp" end="24" id="24" rel="mod">
                    <node begin="13" end="14" frame="preposition(van,[af,uit,vandaan,[af,aan]])" his="normal" his_1="normal" id="25" lcat="pp" lemma="van" pos="prep" postag="VZ(init)" pt="vz" rel="hd" root="van" sense="van" vztype="init" word="van"/>
                    <node begin="14" cat="np" end="24" id="26" rel="obj1">
                      <node begin="14" end="15" frame="noun(de,mass,sg)" gen="de" genus="zijd" getal="ev" graad="basis" his="normal" his_1="normal" id="27" lcat="np" lemma="bewondering" naamval="stan" ntype="soort" num="sg" pos="noun" postag="N(soort,ev,basis,zijd,stan)" pt="n" rel="hd" rnum="sg" root="bewondering" sense="bewondering" word="bewondering"/>
                      <node begin="15" cat="mwu" end="18" his="name" his_1="not_begin" id="28" mwu_root="van den Franschman" mwu_sense="van den Franschman" rel="app">
                        <node begin="15" end="16" frame="proper_name(sg,'PER')" id="29" lcat="np" lemma="van" neclass="PER" num="sg" pos="name" postag="SPEC(deeleigen)" pt="spec" rel="mwp" rnum="sg" root="van" sense="van" spectype="deeleigen" word="van"/>
                        <node begin="16" end="17" frame="proper_name(sg,'PER')" id="30" lcat="np" lemma="den" neclass="PER" num="sg" pos="name" postag="SPEC(deeleigen)" pt="spec" rel="mwp" rnum="sg" root="den" sense="den" spectype="deeleigen" word="den"/>
                        <node begin="17" end="18" frame="proper_name(sg,'PER')" id="31" lcat="np" lemma="Franschman" neclass="PER" num="sg" pos="name" postag="SPEC(deeleigen)" pt="spec" rel="mwp" rnum="sg" root="Franschman" sense="Franschman" spectype="deeleigen" word="Franschman"/>
                      </node>
                      <node begin="18" cat="pp" end="24" id="32" rel="mod">
                        <node begin="18" end="19" frame="preposition(voor,[aan,door,uit,[in,de,plaats]])" his="normal" his_1="normal" id="33" lcat="pp" lemma="voor" pos="prep" postag="VZ(init)" pt="vz" rel="hd" root="voor" sense="voor" vztype="init" word="voor"/>
                        <node begin="20" cat="mwu" end="24" his="name" his_1="begin" id="34" mwu_root="den eenigen Sherlock Holmes" mwu_sense="den eenigen Sherlock Holmes" rel="obj1">
                          <node begin="20" end="21" frame="proper_name(both)" id="35" lcat="np" lemma="den" neclass="MISC" num="both" pos="name" postag="SPEC(deeleigen)" pt="spec" rel="mwp" rnum="sg" root="den" sense="den" spectype="deeleigen" word="den"/>
                          <node begin="21" end="22" frame="proper_name(both)" id="36" lcat="np" lemma="eenigen" neclass="MISC" num="both" pos="name" postag="SPEC(deeleigen)" pt="spec" rel="mwp" rnum="sg" root="eenigen" sense="eenigen" spectype="deeleigen" word="eenigen"/>
                          <node begin="22" end="23" frame="proper_name(both)" id="37" lcat="np" lemma="Sherlock" neclass="MISC" num="both" pos="name" postag="SPEC(deeleigen)" pt="spec" rel="mwp" rnum="sg" root="Sherlock" sense="Sherlock" spectype="deeleigen" word="Sherlock"/>
                          <node begin="23" end="24" frame="proper_name(both)" id="38" lcat="np" lemma="Holmes" neclass="MISC" num="both" pos="name" postag="SPEC(deeleigen)" pt="spec" rel="mwp" rnum="sg" root="Holmes" sense="Holmes" spectype="deeleigen" word="Holmes"/>
                        </node>
                      </node>
                    </node>
                  </node>
                </node>
              </node>
            </node>
            <node begin="25" end="26" frame="verb(hebben,past(sg),ninv(transitive,part_transitive(op)))" his="normal" his_1="part-V" id="39" infl="sg" lcat="ssub" lemma="op_merken" pos="verb" postag="WW(pv,verl,ev)" pt="ww" pvagr="ev" pvtijd="verl" rel="hd" root="merk_op" sc="part_transitive(op)" sense="merk_op" tense="past" word="opmerkte" wvorm="pv"/>
          </node>
        </node>
      </node>
    </node>
    <node begin="26" end="27" frame="punct(punt)" his="robust_skip" id="40" lcat="--" lemma="." pos="punct" postag="LET()" pt="let" rel="--" root="." sense="." special="punt" word="."/>
  </node>
  <sentence sentid="20-2">Ik wierp er een haastigen blik overheen , waarbij ik niets dan betuigingen van bewondering van den Franschman voor &quot; den eenigen Sherlock Holmes &quot; opmerkte .</sentence>
  <comments>
    <comment>Q#20-2|Ik wierp er een haastigen blik overheen , waarbij ik niets dan betuigingen van bewondering van den Franschman voor &quot; den eenigen Sherlock Holmes &quot; opmerkte .|1|2|8.149562530199994</comment>
  </comments>
</alpino_ds>
